README.md
setup.py
pyweibo_picbed/__init__.py
pyweibo_picbed/weibo_picbed.py
pyweibo_picbed.egg-info/PKG-INFO
pyweibo_picbed.egg-info/SOURCES.txt
pyweibo_picbed.egg-info/dependency_links.txt
pyweibo_picbed.egg-info/requires.txt
pyweibo_picbed.egg-info/top_level.txt